MANIFEST.in
buildout.cfg
develop.cfg
requirements.txt
setup.cfg
setup.py
docs/CHANGES.rst
docs/LICENSE.md
docs/README.md
docs/README.rst
src/senaite/__init__.py
src/senaite.ldap.egg-info/PKG-INFO
src/senaite.ldap.egg-info/SOURCES.txt
src/senaite.ldap.egg-info/dependency_links.txt
src/senaite.ldap.egg-info/entry_points.txt
src/senaite.ldap.egg-info/namespace_packages.txt
src/senaite.ldap.egg-info/not-zip-safe
src/senaite.ldap.egg-info/requires.txt
src/senaite.ldap.egg-info/top_level.txt
src/senaite/ldap/__init__.py
src/senaite/ldap/configure.zcml
src/senaite/ldap/interfaces.py
src/senaite/ldap/setuphandlers.py
src/senaite/ldap/browser/__init__.py
src/senaite/ldap/browser/configure.zcml
src/senaite/ldap/browser/controlpanel.py
src/senaite/ldap/browser/static/images/senaite.svg
src/senaite/ldap/browser/templates/controlpanel.pt
src/senaite/ldap/browser/theme/__init__.py
src/senaite/ldap/browser/theme/configure.zcml
src/senaite/ldap/browser/theme/icons.py
src/senaite/ldap/locales/senaite.ldap.pot
src/senaite/ldap/locales/en/LC_MESSAGES/plone-override.po
src/senaite/ldap/locales/en/LC_MESSAGES/senaite.core-override.po
src/senaite/ldap/locales/en/LC_MESSAGES/senaite.core.po
src/senaite/ldap/locales/en/LC_MESSAGES/senaite.ldap.po
src/senaite/ldap/profiles/default/browserlayer.xml
src/senaite/ldap/profiles/default/metadata.xml
src/senaite/ldap/profiles/default/senaite.ldap.txt
src/senaite/ldap/profiles/uninstall/browserlayer.xml
src/senaite/ldap/profiles/uninstall/metadata.xml
src/senaite/ldap/profiles/uninstall/senaite.ldap.uninstall.txt
src/senaite/ldap/tests/__init__.py
src/senaite/ldap/tests/base.py
src/senaite/ldap/tests/test_doctests.py
src/senaite/ldap/tests/test_setup.py
templates/update_sources.in
templates/update_translations.in