Metadata-Version: 2.1
Name: senaite.ldap
Version: 1.0.0
Summary: PAS Plugin for AD/LDAP
Home-page: https://github.com/senaite/senaite.ldap
Author: RIDING BYTES & NARALABS
Author-email: senaite@senaite.com
License: GPLv2
Keywords: senaite,lims
Platform: UNKNOWN
Classifier: Framework :: Plone
Classifier: Framework :: Zope2
Classifier: Programming Language :: Python
Classifier: Development Status :: 5 - Production/Stable
Classifier: License :: OSI Approved :: GNU General Public License v2 (GPLv2)
Provides-Extra: test
